README.md
setup.cfg
setup.py
lapps/__init__.py
lapps/client.py
lapps/discriminators.py
lapps/lif.py
lapps.egg-info/PKG-INFO
lapps.egg-info/SOURCES.txt
lapps.egg-info/dependency_links.txt
lapps.egg-info/requires.txt
lapps.egg-info/top_level.txt