Metadata-Version: 1.1
Name: lapps
Version: 0.0.2
Summary: Python API for the Language Applications Grid
Home-page: https://github.com/lappsgrid-incubator/python-api
Author: Keith Suderman
Author-email: suderman@cs.vassar.edu
License: UNKNOWN
Download-URL: https://github.com/lappsgrid-incubator/python-api/archive/0.0.2.tar.gz
Keywords: lapps,lappsgrid,nlp,web services
Platform: UNKNOWN
